GeomTools/CheckElement.py
GeomTools/CheckModel.py
GeomTools/GeometricFunctions.py
GeomTools/Selector.py
GeomTools/Utils.py
GeomTools/__init__.py
checkifc-0.0.7.dist-info/LICENCE
checkifc-0.0.7.dist-info/METADATA
checkifc-0.0.7.dist-info/WHEEL
checkifc-0.0.7.dist-info/top_level.txt
checkifc-0.0.7.dist-info/RECORD
